LICENSE
grepy/__init__.py
grepy/__main__.py
grepy/core.py
grepy-0.2.0.dist-info/entry_points.txt
grepy-0.2.0.dist-info/LICENSE
grepy-0.2.0.dist-info/WHEEL
grepy-0.2.0.dist-info/METADATA
grepy-0.2.0.dist-info/RECORD
