Metadata-Version: 2.1
Name: grepy
Version: 0.2.0
Summary: A Grep clone
Home-page: https://github.com/UltiRequiem/grep
License: MIT
Keywords: commands,utilities,cli,grep
Author: Eliaz Bobadilla
Author-email: eliaz.bobadilladev@gmail.com
Requires-Python: >=3.8,<4.0
Classifier: License :: OSI Approved :: MIT License
Classifier: Programming Language :: Python :: 3
Classifier: Programming Language :: Python :: 3.8
Classifier: Programming Language :: Python :: 3.9
Project-URL: Repository, https://github.com/UltiRequiem/grep
